{
  "items": [
    {
      "inspection_code": "U-REPLAY-IP-LINK-01",
      "item_id": 90025,
      "application_id": 124,
      "application_type_id": 10,
      "application_type_name": "LINUX",
      "application_name": "A",
      "application_family_name": "A",
      "threshold_list": [
        {
          "name": "exclude_interface_name_patterns",
          "value1": "^lo$|^br-.*|^docker.*|^veth.*"
        }
      ],
      "check_script": "# -*- coding: utf-8 -*-\n\nimport re\n\nfrom .common._base import BaseCheck\n\n\nIP_LINK_COMMAND = 'ip link'\nDEFAULT_EXCLUDE_INTERFACE_NAME_PATTERNS = '^lo$|^br-.*|^docker.*|^veth.*'\nINTERFACE_HEADER_PATTERN = re.compile(\n    r'^\\d+:\\s+(?P<name>[^:]+):\\s+<(?P<flags>[^>]*)>.*\\bstate\\s+(?P<state>[A-Z_]+)\\b',\n    re.IGNORECASE,\n)\n\n\nclass Check(BaseCheck):\n    USE_HOST_CONNECTION = True\n    CONNECTION_METHOD = 'ssh'\n\n    def _split_patterns(self, raw_value):\n        return [\n            token.strip()\n            for token in str(raw_value or '').split('|')\n            if token.strip()\n        ]\n\n    def _normalize_name(self, name):\n        return str(name or '').strip().split('@', 1)[0]\n\n    def _matches_any_pattern(self, name, patterns):\n        return any(\n            re.search(pattern, name)\n            for pattern in patterns\n        )\n\n    def _parse_interfaces(self, stdout):\n        interfaces = []\n\n        for raw_line in (stdout or '').splitlines():\n            match = INTERFACE_HEADER_PATTERN.match(raw_line.strip())\n            if not match:\n                continue\n\n            raw_name = match.group('name').strip()\n            flags = [\n                flag.strip().upper()\n                for flag in match.group('flags').split(',')\n                if flag.strip()\n            ]\n            state = match.group('state').strip().upper()\n            interfaces.append({\n                'name': self._normalize_name(raw_name),\n                'raw_name': raw_name,\n                'flags': flags,\n                'state': state,\n            })\n\n        if not interfaces:\n            raise ValueError('ip link 출력에서 인터페이스 헤더를 찾지 못했습니다.')\n\n        return interfaces\n\n    def _classify_interface(self, interface):\n        flags = set(interface.get('flags') or [])\n        state = str(interface.get('state') or '').upper()\n\n        if state == 'UP' and 'LOWER_UP' in flags and 'NO-CARRIER' not in flags:\n            return 'ok', 'up_lower_up'\n\n        if state == 'UNKNOWN':\n            return 'warn', 'unknown_state'\n\n        if state in ('DOWN', 'DORMANT', 'LOWERLAYERDOWN', 'NOTPRESENT') or 'NO-CARRIER' in flags:\n            return 'warn', 'link_down_or_no_carrier'\n\n        if state == 'UP':\n            return 'warn', 'up_without_lower_up'\n\n        return 'warn', 'unexpected_state'\n\n    def _build_metrics(self, interfaces, excluded_interfaces, target_interfaces, missing_expected_patterns):\n        return {\n            'interface_count': len(interfaces),\n            'excluded_interface_count': len(excluded_interfaces),\n            'target_interface_count': len(target_interfaces),\n            'ok_interface_count': sum(1 for item in target_interfaces if item.get('evaluation') == 'ok'),\n            'warn_interface_count': sum(1 for item in target_interfaces if item.get('evaluation') == 'warn'),\n            'excluded_interfaces': excluded_interfaces,\n            'interfaces': target_interfaces,\n            'missing_expected_interface_name_patterns': missing_expected_patterns,\n        }\n\n    def _format_interfaces(self, interfaces):\n        return ', '.join(\n            f\"{item.get('name')}={item.get('state')}\"\n            for item in interfaces\n        ) or '없음'\n\n    def _format_patterns(self, patterns):\n        return '|'.join(patterns) if patterns else '없음'\n\n    def _format_thresholds(self, exclude_patterns, expected_patterns):\n        return (\n            f'exclude_interface_name_patterns={self._format_patterns(exclude_patterns)}, '\n            f'expected_interface_name_patterns={self._format_patterns(expected_patterns)}'\n        )\n\n    def run(self):\n        exclude_patterns = self._split_patterns(\n            self.get_threshold_var(\n                'exclude_interface_name_patterns',\n                default=DEFAULT_EXCLUDE_INTERFACE_NAME_PATTERNS,\n                value_type='str',\n            )\n        )\n        expected_patterns = self._split_patterns(\n            self.get_threshold_var(\n                'expected_interface_name_patterns',\n                default='',\n                value_type='str',\n            )\n        )\n        rc, out, err = self._ssh(IP_LINK_COMMAND)\n\n        if self._is_connection_error(rc, err):\n            return self.fail(\n                '호스트 연결 실패',\n                message=(err or 'SSH 연결 확인에 실패했습니다.').strip(),\n                stderr=(err or '').strip(),\n            )\n\n        if rc != 0:\n            return self.fail(\n                '점검 명령 실행 실패',\n                message='ip link 명령 실행에 실패했습니다.',\n                stdout=(out or '').strip(),\n                stderr=(err or '').strip(),\n            )\n\n        try:\n            interfaces = self._parse_interfaces(out)\n        except ValueError as exc:\n            return self.fail(\n                '네트워크 링크 상태 파싱 실패',\n                message=str(exc),\n                stdout=(out or '').strip(),\n                stderr=(err or '').strip(),\n            )\n\n        excluded_interfaces = []\n        target_interfaces = []\n\n        for interface in interfaces:\n            normalized_name = interface.get('name') or ''\n            if self._matches_any_pattern(normalized_name, exclude_patterns):\n                excluded_interface = dict(interface)\n                excluded_interface['excluded'] = True\n                excluded_interfaces.append(excluded_interface)\n                continue\n\n            evaluation, evaluation_reason = self._classify_interface(interface)\n            target_interface = dict(interface)\n            target_interface['excluded'] = False\n            target_interface['evaluation'] = evaluation\n            target_interface['evaluation_reason'] = evaluation_reason\n            target_interfaces.append(target_interface)\n\n        if not target_interfaces:\n            return self.fail(\n                '점검 대상 NIC 없음',\n                message=(\n                    '제외 패턴 적용 후 점검할 네트워크 인터페이스가 없습니다. '\n                    f'임계치 정보: {self._format_thresholds(exclude_patterns, expected_patterns)}. '\n                    f'판단근거: 전체 인터페이스 {len(interfaces)}개 중 '\n                    f'제외된 인터페이스 {len(excluded_interfaces)}개, 점검 대상 0개입니다.'\n                ),\n                stdout=(out or '').strip(),\n                stderr=(err or '').strip(),\n            )\n\n        missing_expected_patterns = [\n            pattern\n            for pattern in expected_patterns\n            if not any(\n                re.search(pattern, interface.get('name') or '')\n                for interface in target_interfaces\n            )\n        ]\n        thresholds = {\n            'exclude_interface_name_patterns': '|'.join(exclude_patterns),\n            'expected_interface_name_patterns': '|'.join(expected_patterns),\n        }\n        metrics = self._build_metrics(\n            interfaces,\n            excluded_interfaces,\n            target_interfaces,\n            missing_expected_patterns,\n        )\n        warning_interfaces = [\n            interface\n            for interface in target_interfaces\n            if interface.get('evaluation') == 'warn'\n        ]\n\n        reasons = []\n        if warning_interfaces:\n            reasons.append(\n                '추가 확인이 필요한 NIC 상태: ' + self._format_interfaces(warning_interfaces)\n            )\n        if missing_expected_patterns:\n            reasons.append(\n                '기대한 NIC 이름 패턴이 확인되지 않았습니다: ' + ', '.join(missing_expected_patterns)\n            )\n\n        if reasons:\n            return self.warn(\n                metrics=metrics,\n                thresholds=thresholds,\n                reasons='; '.join(reasons),\n                message=(\n                    'NW 링크 상태 추가 확인 필요. '\n                    f'임계치 정보: {self._format_thresholds(exclude_patterns, expected_patterns)}. '\n                    '판단기준: 제외 패턴 적용 후 점검 대상 NIC는 '\n                    'state=UP, LOWER_UP 플래그 보유, NO-CARRIER 미포함이어야 하며 '\n                    '기대 NIC 패턴이 모두 확인되어야 합니다. '\n                    f'판단근거: warning_interfaces={self._format_interfaces(warning_interfaces)}, '\n                    f'missing_expected_patterns={self._format_patterns(missing_expected_patterns)}, '\n                    f'target_interface_count={len(target_interfaces)}.'\n                ),\n            )\n\n        return self.ok(\n            metrics=metrics,\n            thresholds=thresholds,\n            reasons=(\n                f'점검 대상 NIC {len(target_interfaces)}개가 모두 UP, LOWER_UP 상태이며 '\n                '기대 NIC 패턴 누락이 없습니다.'\n            ),\n            message=(\n                'ip link 기준 NW 링크 상태 점검이 정상 수행되었습니다. '\n                f'임계치 정보: {self._format_thresholds(exclude_patterns, expected_patterns)}. '\n                '판단기준: 제외 패턴 적용 후 점검 대상 NIC는 '\n                'state=UP, LOWER_UP 플래그 보유, NO-CARRIER 미포함이어야 하며 '\n                '기대 NIC 패턴이 모두 확인되어야 합니다. '\n                f'판단근거: target_interface_count={len(target_interfaces)}, '\n                f'ok_interface_count={metrics[\"ok_interface_count\"]}, '\n                f'warn_interface_count={metrics[\"warn_interface_count\"]}.'\n            ),\n        )\n\n\nCHECK_CLASS = Check\n",
      "check_script_lines": [
        "# -*- coding: utf-8 -*-",
        "",
        "import re",
        "",
        "from .common._base import BaseCheck",
        "",
        "",
        "IP_LINK_COMMAND = 'ip link'",
        "DEFAULT_EXCLUDE_INTERFACE_NAME_PATTERNS = '^lo$|^br-.*|^docker.*|^veth.*'",
        "INTERFACE_HEADER_PATTERN = re.compile(",
        "    r'^\\d+:\\s+(?P<name>[^:]+):\\s+<(?P<flags>[^>]*)>.*\\bstate\\s+(?P<state>[A-Z_]+)\\b',",
        "    re.IGNORECASE,",
        ")",
        "",
        "",
        "class Check(BaseCheck):",
        "    USE_HOST_CONNECTION = True",
        "    CONNECTION_METHOD = 'ssh'",
        "",
        "    def _split_patterns(self, raw_value):",
        "        return [",
        "            token.strip()",
        "            for token in str(raw_value or '').split('|')",
        "            if token.strip()",
        "        ]",
        "",
        "    def _normalize_name(self, name):",
        "        return str(name or '').strip().split('@', 1)[0]",
        "",
        "    def _matches_any_pattern(self, name, patterns):",
        "        return any(",
        "            re.search(pattern, name)",
        "            for pattern in patterns",
        "        )",
        "",
        "    def _parse_interfaces(self, stdout):",
        "        interfaces = []",
        "",
        "        for raw_line in (stdout or '').splitlines():",
        "            match = INTERFACE_HEADER_PATTERN.match(raw_line.strip())",
        "            if not match:",
        "                continue",
        "",
        "            raw_name = match.group('name').strip()",
        "            flags = [",
        "                flag.strip().upper()",
        "                for flag in match.group('flags').split(',')",
        "                if flag.strip()",
        "            ]",
        "            state = match.group('state').strip().upper()",
        "            interfaces.append({",
        "                'name': self._normalize_name(raw_name),",
        "                'raw_name': raw_name,",
        "                'flags': flags,",
        "                'state': state,",
        "            })",
        "",
        "        if not interfaces:",
        "            raise ValueError('ip link 출력에서 인터페이스 헤더를 찾지 못했습니다.')",
        "",
        "        return interfaces",
        "",
        "    def _classify_interface(self, interface):",
        "        flags = set(interface.get('flags') or [])",
        "        state = str(interface.get('state') or '').upper()",
        "",
        "        if state == 'UP' and 'LOWER_UP' in flags and 'NO-CARRIER' not in flags:",
        "            return 'ok', 'up_lower_up'",
        "",
        "        if state == 'UNKNOWN':",
        "            return 'warn', 'unknown_state'",
        "",
        "        if state in ('DOWN', 'DORMANT', 'LOWERLAYERDOWN', 'NOTPRESENT') or 'NO-CARRIER' in flags:",
        "            return 'warn', 'link_down_or_no_carrier'",
        "",
        "        if state == 'UP':",
        "            return 'warn', 'up_without_lower_up'",
        "",
        "        return 'warn', 'unexpected_state'",
        "",
        "    def _build_metrics(self, interfaces, excluded_interfaces, target_interfaces, missing_expected_patterns):",
        "        return {",
        "            'interface_count': len(interfaces),",
        "            'excluded_interface_count': len(excluded_interfaces),",
        "            'target_interface_count': len(target_interfaces),",
        "            'ok_interface_count': sum(1 for item in target_interfaces if item.get('evaluation') == 'ok'),",
        "            'warn_interface_count': sum(1 for item in target_interfaces if item.get('evaluation') == 'warn'),",
        "            'excluded_interfaces': excluded_interfaces,",
        "            'interfaces': target_interfaces,",
        "            'missing_expected_interface_name_patterns': missing_expected_patterns,",
        "        }",
        "",
        "    def _format_interfaces(self, interfaces):",
        "        return ', '.join(",
        "            f\"{item.get('name')}={item.get('state')}\"",
        "            for item in interfaces",
        "        ) or '없음'",
        "",
        "    def _format_patterns(self, patterns):",
        "        return '|'.join(patterns) if patterns else '없음'",
        "",
        "    def _format_thresholds(self, exclude_patterns, expected_patterns):",
        "        return (",
        "            f'exclude_interface_name_patterns={self._format_patterns(exclude_patterns)}, '",
        "            f'expected_interface_name_patterns={self._format_patterns(expected_patterns)}'",
        "        )",
        "",
        "    def run(self):",
        "        exclude_patterns = self._split_patterns(",
        "            self.get_threshold_var(",
        "                'exclude_interface_name_patterns',",
        "                default=DEFAULT_EXCLUDE_INTERFACE_NAME_PATTERNS,",
        "                value_type='str',",
        "            )",
        "        )",
        "        expected_patterns = self._split_patterns(",
        "            self.get_threshold_var(",
        "                'expected_interface_name_patterns',",
        "                default='',",
        "                value_type='str',",
        "            )",
        "        )",
        "        rc, out, err = self._ssh(IP_LINK_COMMAND)",
        "",
        "        if self._is_connection_error(rc, err):",
        "            return self.fail(",
        "                '호스트 연결 실패',",
        "                message=(err or 'SSH 연결 확인에 실패했습니다.').strip(),",
        "                stderr=(err or '').strip(),",
        "            )",
        "",
        "        if rc != 0:",
        "            return self.fail(",
        "                '점검 명령 실행 실패',",
        "                message='ip link 명령 실행에 실패했습니다.',",
        "                stdout=(out or '').strip(),",
        "                stderr=(err or '').strip(),",
        "            )",
        "",
        "        try:",
        "            interfaces = self._parse_interfaces(out)",
        "        except ValueError as exc:",
        "            return self.fail(",
        "                '네트워크 링크 상태 파싱 실패',",
        "                message=str(exc),",
        "                stdout=(out or '').strip(),",
        "                stderr=(err or '').strip(),",
        "            )",
        "",
        "        excluded_interfaces = []",
        "        target_interfaces = []",
        "",
        "        for interface in interfaces:",
        "            normalized_name = interface.get('name') or ''",
        "            if self._matches_any_pattern(normalized_name, exclude_patterns):",
        "                excluded_interface = dict(interface)",
        "                excluded_interface['excluded'] = True",
        "                excluded_interfaces.append(excluded_interface)",
        "                continue",
        "",
        "            evaluation, evaluation_reason = self._classify_interface(interface)",
        "            target_interface = dict(interface)",
        "            target_interface['excluded'] = False",
        "            target_interface['evaluation'] = evaluation",
        "            target_interface['evaluation_reason'] = evaluation_reason",
        "            target_interfaces.append(target_interface)",
        "",
        "        if not target_interfaces:",
        "            return self.fail(",
        "                '점검 대상 NIC 없음',",
        "                message=(",
        "                    '제외 패턴 적용 후 점검할 네트워크 인터페이스가 없습니다. '",
        "                    f'임계치 정보: {self._format_thresholds(exclude_patterns, expected_patterns)}. '",
        "                    f'판단근거: 전체 인터페이스 {len(interfaces)}개 중 '",
        "                    f'제외된 인터페이스 {len(excluded_interfaces)}개, 점검 대상 0개입니다.'",
        "                ),",
        "                stdout=(out or '').strip(),",
        "                stderr=(err or '').strip(),",
        "            )",
        "",
        "        missing_expected_patterns = [",
        "            pattern",
        "            for pattern in expected_patterns",
        "            if not any(",
        "                re.search(pattern, interface.get('name') or '')",
        "                for interface in target_interfaces",
        "            )",
        "        ]",
        "        thresholds = {",
        "            'exclude_interface_name_patterns': '|'.join(exclude_patterns),",
        "            'expected_interface_name_patterns': '|'.join(expected_patterns),",
        "        }",
        "        metrics = self._build_metrics(",
        "            interfaces,",
        "            excluded_interfaces,",
        "            target_interfaces,",
        "            missing_expected_patterns,",
        "        )",
        "        warning_interfaces = [",
        "            interface",
        "            for interface in target_interfaces",
        "            if interface.get('evaluation') == 'warn'",
        "        ]",
        "",
        "        reasons = []",
        "        if warning_interfaces:",
        "            reasons.append(",
        "                '추가 확인이 필요한 NIC 상태: ' + self._format_interfaces(warning_interfaces)",
        "            )",
        "        if missing_expected_patterns:",
        "            reasons.append(",
        "                '기대한 NIC 이름 패턴이 확인되지 않았습니다: ' + ', '.join(missing_expected_patterns)",
        "            )",
        "",
        "        if reasons:",
        "            return self.warn(",
        "                metrics=metrics,",
        "                thresholds=thresholds,",
        "                reasons='; '.join(reasons),",
        "                message=(",
        "                    'NW 링크 상태 추가 확인 필요. '",
        "                    f'임계치 정보: {self._format_thresholds(exclude_patterns, expected_patterns)}. '",
        "                    '판단기준: 제외 패턴 적용 후 점검 대상 NIC는 '",
        "                    'state=UP, LOWER_UP 플래그 보유, NO-CARRIER 미포함이어야 하며 '",
        "                    '기대 NIC 패턴이 모두 확인되어야 합니다. '",
        "                    f'판단근거: warning_interfaces={self._format_interfaces(warning_interfaces)}, '",
        "                    f'missing_expected_patterns={self._format_patterns(missing_expected_patterns)}, '",
        "                    f'target_interface_count={len(target_interfaces)}.'",
        "                ),",
        "            )",
        "",
        "        return self.ok(",
        "            metrics=metrics,",
        "            thresholds=thresholds,",
        "            reasons=(",
        "                f'점검 대상 NIC {len(target_interfaces)}개가 모두 UP, LOWER_UP 상태이며 '",
        "                '기대 NIC 패턴 누락이 없습니다.'",
        "            ),",
        "            message=(",
        "                'ip link 기준 NW 링크 상태 점검이 정상 수행되었습니다. '",
        "                f'임계치 정보: {self._format_thresholds(exclude_patterns, expected_patterns)}. '",
        "                '판단기준: 제외 패턴 적용 후 점검 대상 NIC는 '",
        "                'state=UP, LOWER_UP 플래그 보유, NO-CARRIER 미포함이어야 하며 '",
        "                '기대 NIC 패턴이 모두 확인되어야 합니다. '",
        "                f'판단근거: target_interface_count={len(target_interfaces)}, '",
        "                f'ok_interface_count={metrics[\"ok_interface_count\"]}, '",
        "                f'warn_interface_count={metrics[\"warn_interface_count\"]}.'",
        "            ),",
        "        )",
        "",
        "",
        "CHECK_CLASS = Check"
      ]
    }
  ],
  "results": [
    {
      "inspection_code": "U-REPLAY-IP-LINK-01",
      "item_id": 90025,
      "application_id": 124,
      "application_type_id": 10,
      "application_type_name": "LINUX",
      "application_name": "A",
      "application_family_name": "A",
      "threshold_list": [
        {
          "name": "exclude_interface_name_patterns",
          "value1": "^lo$|^br-.*|^docker.*|^veth.*"
        }
      ],
      "status": "warn",
      "metrics": {
        "interface_count": 18,
        "excluded_interface_count": 14,
        "target_interface_count": 4,
        "ok_interface_count": 1,
        "warn_interface_count": 3,
        "excluded_interfaces": [
          {
            "name": "lo",
            "raw_name": "lo",
            "flags": [
              "LOOPBACK",
              "UP",
              "LOWER_UP"
            ],
            "state": "UNKNOWN",
            "excluded": true
          },
          {
            "name": "br-b687e047b713",
            "raw_name": "br-b687e047b713",
            "flags": [
              "NO-CARRIER",
              "BROADCAST",
              "MULTICAST",
              "UP"
            ],
            "state": "DOWN",
            "excluded": true
          },
          {
            "name": "br-3e40457894eb",
            "raw_name": "br-3e40457894eb",
            "flags": [
              "NO-CARRIER",
              "BROADCAST",
              "MULTICAST",
              "UP"
            ],
            "state": "DOWN",
            "excluded": true
          },
          {
            "name": "docker0",
            "raw_name": "docker0",
            "flags": [
              "BROADCAST",
              "MULTICAST",
              "UP",
              "LOWER_UP"
            ],
            "state": "UP",
            "excluded": true
          },
          {
            "name": "br-6a04ef950573",
            "raw_name": "br-6a04ef950573",
            "flags": [
              "NO-CARRIER",
              "BROADCAST",
              "MULTICAST",
              "UP"
            ],
            "state": "DOWN",
            "excluded": true
          },
          {
            "name": "veth32719e4",
            "raw_name": "veth32719e4@if2",
            "flags": [
              "BROADCAST",
              "MULTICAST",
              "UP",
              "LOWER_UP"
            ],
            "state": "UP",
            "excluded": true
          },
          {
            "name": "veth6291e48",
            "raw_name": "veth6291e48@if2",
            "flags": [
              "BROADCAST",
              "MULTICAST",
              "UP",
              "LOWER_UP"
            ],
            "state": "UP",
            "excluded": true
          },
          {
            "name": "br-ed17885ef5c2",
            "raw_name": "br-ed17885ef5c2",
            "flags": [
              "NO-CARRIER",
              "BROADCAST",
              "MULTICAST",
              "UP"
            ],
            "state": "DOWN",
            "excluded": true
          },
          {
            "name": "docker_gwbridge",
            "raw_name": "docker_gwbridge",
            "flags": [
              "BROADCAST",
              "MULTICAST",
              "UP",
              "LOWER_UP"
            ],
            "state": "UP",
            "excluded": true
          },
          {
            "name": "veth93dbdec",
            "raw_name": "veth93dbdec@if281",
            "flags": [
              "BROADCAST",
              "MULTICAST",
              "UP",
              "LOWER_UP"
            ],
            "state": "UP",
            "excluded": true
          },
          {
            "name": "vethda7d78b",
            "raw_name": "vethda7d78b@if292",
            "flags": [
              "BROADCAST",
              "MULTICAST",
              "UP",
              "LOWER_UP"
            ],
            "state": "UP",
            "excluded": true
          },
          {
            "name": "vethe9072c6",
            "raw_name": "vethe9072c6@if2",
            "flags": [
              "BROADCAST",
              "MULTICAST",
              "UP",
              "LOWER_UP"
            ],
            "state": "UP",
            "excluded": true
          },
          {
            "name": "br-c05f4f389f6a",
            "raw_name": "br-c05f4f389f6a",
            "flags": [
              "BROADCAST",
              "MULTICAST",
              "UP",
              "LOWER_UP"
            ],
            "state": "UP",
            "excluded": true
          },
          {
            "name": "veth73eb6b0",
            "raw_name": "veth73eb6b0@if2",
            "flags": [
              "BROADCAST",
              "MULTICAST",
              "UP",
              "LOWER_UP"
            ],
            "state": "UP",
            "excluded": true
          }
        ],
        "interfaces": [
          {
            "name": "eno1",
            "raw_name": "eno1",
            "flags": [
              "BROADCAST",
              "MULTICAST",
              "UP",
              "LOWER_UP"
            ],
            "state": "UP",
            "excluded": false,
            "evaluation": "ok",
            "evaluation_reason": "up_lower_up"
          },
          {
            "name": "eno2",
            "raw_name": "eno2",
            "flags": [
              "NO-CARRIER",
              "BROADCAST",
              "MULTICAST",
              "UP"
            ],
            "state": "DOWN",
            "excluded": false,
            "evaluation": "warn",
            "evaluation_reason": "link_down_or_no_carrier"
          },
          {
            "name": "enp129s0f0",
            "raw_name": "enp129s0f0",
            "flags": [
              "NO-CARRIER",
              "BROADCAST",
              "MULTICAST",
              "UP"
            ],
            "state": "DOWN",
            "excluded": false,
            "evaluation": "warn",
            "evaluation_reason": "link_down_or_no_carrier"
          },
          {
            "name": "enp129s0f1",
            "raw_name": "enp129s0f1",
            "flags": [
              "NO-CARRIER",
              "BROADCAST",
              "MULTICAST",
              "UP"
            ],
            "state": "DOWN",
            "excluded": false,
            "evaluation": "warn",
            "evaluation_reason": "link_down_or_no_carrier"
          }
        ],
        "missing_expected_interface_name_patterns": []
      },
      "thresholds": {
        "exclude_interface_name_patterns": "^lo$|^br-.*|^docker.*|^veth.*",
        "expected_interface_name_patterns": ""
      },
      "reasons": "추가 확인이 필요한 NIC 상태: eno2=DOWN, enp129s0f0=DOWN, enp129s0f1=DOWN",
      "message": "NW 링크 상태 추가 확인 필요. 임계치 정보: exclude_interface_name_patterns=^lo$|^br-.*|^docker.*|^veth.*, expected_interface_name_patterns=없음. 판단기준: 제외 패턴 적용 후 점검 대상 NIC는 state=UP, LOWER_UP 플래그 보유, NO-CARRIER 미포함이어야 하며 기대 NIC 패턴이 모두 확인되어야 합니다. 판단근거: warning_interfaces=eno2=DOWN, enp129s0f0=DOWN, enp129s0f1=DOWN, missing_expected_patterns=없음, target_interface_count=4.",
      "raw_output": "[점검 단계 1]\n - 실행 명령어: ip link\n - 명령 종료코드: rc=0 (정상 종료)\n - 출력 내용: 1: lo: <LOOPBACK,UP,LOWER_UP> mtu 65536 qdisc noqueue state UNKNOWN mode DEFAULT group default qlen 1000\n    link/loopback 00:00:00:00:00:00 brd 00:00:00:00:00:00\n258: br-b687e047b713: <NO-CARRIER,BROADCAST,MULTICAST,UP> mtu 1500 qdisc noqueue state DOWN mode DEFAULT group default \n    link/ether 0a:a9:67:08:33:43 brd ff:ff:ff:ff:ff:ff\n2: eno1: <BROADCAST,MULTICAST,UP,LOWER_UP> mtu 1500 qdisc mq state UP mode DEFAULT group default qlen 1000\n    link/ether 74:9d:8f:0e:ad:f2 brd ff:ff:ff:ff:ff:ff\n    altname enp2s0f0\n3: eno2: <NO-CARRIER,BROADCAST,MULTICAST,UP> mtu 1500 qdisc mq state DOWN mode DEFAULT group default qlen 1000\n    link/ether 74:9d:8f:0e:ad:f3 brd ff:ff:ff:ff:ff:ff\n    altname enp2s0f1\n4: enp129s0f0: <NO-CARRIER,BROADCAST,MULTICAST,UP> mtu 1500 qdisc mq state DOWN mode DEFAULT group default qlen 1000\n    link/ether 04:27:58:0a:fa:2b brd ff:ff:ff:ff:ff:ff\n5: enp129s0f1: <NO-CARRIER,BROADCAST,MULTICAST,UP> mtu 1500 qdisc mq state DOWN mode DEFAULT group default qlen 1000\n    link/ether 04:27:58:0a:fa:2c brd ff:ff:ff:ff:ff:ff\n6: br-3e40457894eb: <NO-CARRIER,BROADCAST,MULTICAST,UP> mtu 1500 qdisc noqueue state DOWN mode DEFAULT group default \n    link/ether 22:e6:03:db:9a:72 brd ff:ff:ff:ff:ff:ff\n7: docker0: <BROADCAST,MULTICAST,UP,LOWER_UP> mtu 1500 qdisc noqueue state UP mode DEFAULT group default \n    link/ether 06:51:8e:96:c4:5d brd ff:ff:ff:ff:ff:ff\n8: br-6a04ef950573: <NO-CARRIER,BROADCAST,MULTICAST,UP> mtu 1500 qdisc noqueue state DOWN mode DEFAULT group default \n    link/ether 36:03:8e:67:89:f5 brd ff:ff:ff:ff:ff:ff\n524: veth32719e4@if2: <BROADCAST,MULTICAST,UP,LOWER_UP> mtu 1500 qdisc noqueue master br-c05f4f389f6a state UP mode DEFAULT group default \n    link/ether 76:1d:6c:77:8b:c5 brd ff:ff:ff:ff:ff:ff link-netnsid 1\n525: veth6291e48@if2: <BROADCAST,MULTICAST,UP,LOWER_UP> mtu 1500 qdisc noqueue master br-c05f4f389f6a state UP mode DEFAULT group default \n    link/ether 92:74:f7:f8:cd:4e brd ff:ff:ff:ff:ff:ff link-netnsid 2\n14: br-ed17885ef5c2: <NO-CARRIER,BROADCAST,MULTICAST,UP> mtu 1500 qdisc noqueue state DOWN mode DEFAULT group default \n    link/ether ca:ef:a5:bf:46:55 brd ff:ff:ff:ff:ff:ff\n280: docker_gwbridge: <BROADCAST,MULTICAST,UP,LOWER_UP> mtu 1500 qdisc noqueue state UP mode DEFAULT group default \n    link/ether 6e:ca:bc:88:d8:29 brd ff:ff:ff:ff:ff:ff\n282: veth93dbdec@if281: <BROADCAST,MULTICAST,UP,LOWER_UP> mtu 1500 qdisc noqueue master docker_gwbridge state UP mode DEFAULT group default \n    link/ether c2:9d:8b:c2:cb:b5 brd ff:ff:ff:ff:ff:ff link-netnsid 5\n293: vethda7d78b@if292: <BROADCAST,MULTICAST,UP,LOWER_UP> mtu 1500 qdisc noqueue master docker_gwbridge state UP mode DEFAULT group default \n    link/ether 5e:0c:cd:47:0e:7d brd ff:ff:ff:ff:ff:ff link-netnsid 8\n294: vethe9072c6@if2: <BROADCAST,MULTICAST,UP,LOWER_UP> mtu 1500 qdisc noqueue master docker0 state UP mode DEFAULT group default \n    link/ether 26:3a:00:00:e5:90 brd ff:ff:ff:ff:ff:ff link-netnsid 9\n416: br-c05f4f389f6a: <BROADCAST,MULTICAST,UP,LOWER_UP> mtu 1500 qdisc noqueue state UP mode DEFAULT group default \n    link/ether 22:a7:a5:36:a0:0c brd ff:ff:ff:ff:ff:ff\n417: veth73eb6b0@if2: <BROADCAST,MULTICAST,UP,LOWER_UP> mtu 1500 qdisc noqueue master br-c05f4f389f6a state UP mode DEFAULT group default \n    link/ether 86:8c:33:38:1d:df brd ff:ff:ff:ff:ff:ff link-netnsid 0",
      "raw_output_lines": [
        "[점검 단계 1]",
        " - 실행 명령어: ip link",
        " - 명령 종료코드: rc=0 (정상 종료)",
        " - 출력 내용: 1: lo: <LOOPBACK,UP,LOWER_UP> mtu 65536 qdisc noqueue state UNKNOWN mode DEFAULT group default qlen 1000",
        "    link/loopback 00:00:00:00:00:00 brd 00:00:00:00:00:00",
        "258: br-b687e047b713: <NO-CARRIER,BROADCAST,MULTICAST,UP> mtu 1500 qdisc noqueue state DOWN mode DEFAULT group default ",
        "    link/ether 0a:a9:67:08:33:43 brd ff:ff:ff:ff:ff:ff",
        "2: eno1: <BROADCAST,MULTICAST,UP,LOWER_UP> mtu 1500 qdisc mq state UP mode DEFAULT group default qlen 1000",
        "    link/ether 74:9d:8f:0e:ad:f2 brd ff:ff:ff:ff:ff:ff",
        "    altname enp2s0f0",
        "3: eno2: <NO-CARRIER,BROADCAST,MULTICAST,UP> mtu 1500 qdisc mq state DOWN mode DEFAULT group default qlen 1000",
        "    link/ether 74:9d:8f:0e:ad:f3 brd ff:ff:ff:ff:ff:ff",
        "    altname enp2s0f1",
        "4: enp129s0f0: <NO-CARRIER,BROADCAST,MULTICAST,UP> mtu 1500 qdisc mq state DOWN mode DEFAULT group default qlen 1000",
        "    link/ether 04:27:58:0a:fa:2b brd ff:ff:ff:ff:ff:ff",
        "5: enp129s0f1: <NO-CARRIER,BROADCAST,MULTICAST,UP> mtu 1500 qdisc mq state DOWN mode DEFAULT group default qlen 1000",
        "    link/ether 04:27:58:0a:fa:2c brd ff:ff:ff:ff:ff:ff",
        "6: br-3e40457894eb: <NO-CARRIER,BROADCAST,MULTICAST,UP> mtu 1500 qdisc noqueue state DOWN mode DEFAULT group default ",
        "    link/ether 22:e6:03:db:9a:72 brd ff:ff:ff:ff:ff:ff",
        "7: docker0: <BROADCAST,MULTICAST,UP,LOWER_UP> mtu 1500 qdisc noqueue state UP mode DEFAULT group default ",
        "    link/ether 06:51:8e:96:c4:5d brd ff:ff:ff:ff:ff:ff",
        "8: br-6a04ef950573: <NO-CARRIER,BROADCAST,MULTICAST,UP> mtu 1500 qdisc noqueue state DOWN mode DEFAULT group default ",
        "    link/ether 36:03:8e:67:89:f5 brd ff:ff:ff:ff:ff:ff",
        "524: veth32719e4@if2: <BROADCAST,MULTICAST,UP,LOWER_UP> mtu 1500 qdisc noqueue master br-c05f4f389f6a state UP mode DEFAULT group default ",
        "    link/ether 76:1d:6c:77:8b:c5 brd ff:ff:ff:ff:ff:ff link-netnsid 1",
        "525: veth6291e48@if2: <BROADCAST,MULTICAST,UP,LOWER_UP> mtu 1500 qdisc noqueue master br-c05f4f389f6a state UP mode DEFAULT group default ",
        "    link/ether 92:74:f7:f8:cd:4e brd ff:ff:ff:ff:ff:ff link-netnsid 2",
        "14: br-ed17885ef5c2: <NO-CARRIER,BROADCAST,MULTICAST,UP> mtu 1500 qdisc noqueue state DOWN mode DEFAULT group default ",
        "    link/ether ca:ef:a5:bf:46:55 brd ff:ff:ff:ff:ff:ff",
        "280: docker_gwbridge: <BROADCAST,MULTICAST,UP,LOWER_UP> mtu 1500 qdisc noqueue state UP mode DEFAULT group default ",
        "    link/ether 6e:ca:bc:88:d8:29 brd ff:ff:ff:ff:ff:ff",
        "282: veth93dbdec@if281: <BROADCAST,MULTICAST,UP,LOWER_UP> mtu 1500 qdisc noqueue master docker_gwbridge state UP mode DEFAULT group default ",
        "    link/ether c2:9d:8b:c2:cb:b5 brd ff:ff:ff:ff:ff:ff link-netnsid 5",
        "293: vethda7d78b@if292: <BROADCAST,MULTICAST,UP,LOWER_UP> mtu 1500 qdisc noqueue master docker_gwbridge state UP mode DEFAULT group default ",
        "    link/ether 5e:0c:cd:47:0e:7d brd ff:ff:ff:ff:ff:ff link-netnsid 8",
        "294: vethe9072c6@if2: <BROADCAST,MULTICAST,UP,LOWER_UP> mtu 1500 qdisc noqueue master docker0 state UP mode DEFAULT group default ",
        "    link/ether 26:3a:00:00:e5:90 brd ff:ff:ff:ff:ff:ff link-netnsid 9",
        "416: br-c05f4f389f6a: <BROADCAST,MULTICAST,UP,LOWER_UP> mtu 1500 qdisc noqueue state UP mode DEFAULT group default ",
        "    link/ether 22:a7:a5:36:a0:0c brd ff:ff:ff:ff:ff:ff",
        "417: veth73eb6b0@if2: <BROADCAST,MULTICAST,UP,LOWER_UP> mtu 1500 qdisc noqueue master br-c05f4f389f6a state UP mode DEFAULT group default ",
        "    link/ether 86:8c:33:38:1d:df brd ff:ff:ff:ff:ff:ff link-netnsid 0"
      ]
    }
  ],
  "failed_items": []
}
