[
  {
    "matcher_type": "exact",
    "matcher_value": "'==Initiator Ports=='; $ip=Get-InitiatorPort -ErrorAction SilentlyContinue; if($ip){$ip|Select-Object InstanceName,ConnectionType,NodeAddress,PortAddress|Format-Table -Auto}else{'No HBA initiator ports exposed.'}; '==FC Port State=='; $fc=Get-CimInstance -Namespace root\\wmi -Class MSFC_FibrePortHBAAttributes -ErrorAction SilentlyContinue; if($fc){$fc|Select-Object InstanceName,@{N='PortState';E={switch($_.Attributes.PortState){1{'Unknown'}2{'Operational'}3{'User Offline'}4{'Bypassed'}5{'Diagnostics'}6{'Link Down'}7{'Port Error'}8{'Loopback'}default{$_.Attributes.PortState}}}},HBAStatus|Format-Table -Auto}else{'No FC HBA port-state data exposed by driver.'}; '==Recent HBA Events=='; $ev=Get-WinEvent -FilterHashtable @{LogName='System';StartTime=(Get-Date).AddDays(-30);Level=@(1,2,3)} -ErrorAction SilentlyContinue|Where-Object{$_.Message -match '(?i)\\bhba\\b|fibre channel|fiber channel|\\bfc\\b|loopback|link down|port.+offline|port.+online'}; if($ev){$ev|Select-Object -First 50 TimeCreated,ProviderName,Id,LevelDisplayName,@{N='Message';E={($_.Message -replace '\\r?\\n',' ')}}|Format-Table -Wrap -Auto}else{'No HBA/port offline-online-like events found in the last 30 days.'}",
    "rc": 0,
    "stdout_file": "outputs/log_hba.stdout",
    "stderr": ""
  }
]
