{
  "items": [
    {
      "inspection_code": "U-REPLAY-DMESG-01",
      "item_id": 90012,
      "application_id": 111,
      "application_type_id": 10,
      "application_type_name": "LINUX",
      "application_name": "A",
      "application_family_name": "A",
      "threshold_list": [
        {
          "name": "critical_log_keywords",
          "value1": "Out of memory|I/O error|Buffer I/O error|Call Trace|segfault|filesystem error|kernel panic"
        },
        {
          "name": "warning_log_keywords",
          "value1": "temperature above threshold|cpu clock throttled|throttled|reset|timeout"
        }
      ],
      "check_script": "# -*- coding: utf-8 -*-\n\nfrom .common._base import BaseCheck\n\n\nDMESG_COMMAND = 'dmesg'\n\n\nclass Check(BaseCheck):\n    USE_HOST_CONNECTION = True\n    CONNECTION_METHOD = 'ssh'\n\n    def _split_keywords(self, raw_value):\n        return [\n            token.strip()\n            for token in str(raw_value or '').split('|')\n            if token.strip()\n        ]\n\n    def _find_matches(self, lines, keywords):\n        matches = []\n\n        for line in lines:\n            line_lower = line.lower()\n            matched_keywords = [\n                keyword\n                for keyword in keywords\n                if keyword.lower() in line_lower\n            ]\n            if not matched_keywords:\n                continue\n            matches.append({\n                'line': line,\n                'matched_keywords': matched_keywords,\n            })\n\n        return matches\n\n    def _count_keywords(self, matches, keywords):\n        counts = {keyword: 0 for keyword in keywords}\n\n        for match in matches:\n            for keyword in match.get('matched_keywords', []):\n                if keyword in counts:\n                    counts[keyword] += 1\n\n        return counts\n\n    def _format_keyword_counts(self, counts):\n        return ', '.join(\n            f'{keyword}={count}건'\n            for keyword, count in counts.items()\n        )\n\n    def run(self):\n        critical_keywords = self._split_keywords(\n            self.get_threshold_var('critical_log_keywords', default='', value_type='str')\n        )\n        warning_keywords = self._split_keywords(\n            self.get_threshold_var('warning_log_keywords', default='', value_type='str')\n        )\n\n        if not critical_keywords and not warning_keywords:\n            return self.fail(\n                '임계치 미정의',\n                message='critical_log_keywords 또는 warning_log_keywords 가 정의되어 있지 않습니다.',\n            )\n\n        rc, out, err = self._ssh(DMESG_COMMAND)\n\n        if self._is_connection_error(rc, err):\n            return self.fail(\n                '호스트 연결 실패',\n                message=(err or 'SSH 연결 확인에 실패했습니다.').strip(),\n                stderr=(err or '').strip(),\n            )\n\n        if rc != 0:\n            return self.fail(\n                '점검 명령 실행 실패',\n                message='dmesg 명령 실행에 실패했습니다.',\n                stdout=(out or '').strip(),\n                stderr=(err or '').strip(),\n            )\n\n        lines = [line.strip() for line in (out or '').splitlines() if line.strip()]\n        if not lines:\n            return self.fail(\n                '시스템 로그 정보 없음',\n                message='dmesg 결과가 비어 있습니다.',\n                stdout=(out or '').strip(),\n                stderr=(err or '').strip(),\n            )\n\n        critical_matches = self._find_matches(lines, critical_keywords)\n        warning_matches = self._find_matches(lines, warning_keywords)\n        critical_keyword_counts = self._count_keywords(critical_matches, critical_keywords)\n        warning_keyword_counts = self._count_keywords(warning_matches, warning_keywords)\n\n        metrics = {\n            'log_line_count': len(lines),\n            'critical_match_count': len(critical_matches),\n            'warning_match_count': len(warning_matches),\n            'critical_keyword_counts': critical_keyword_counts,\n            'warning_keyword_counts': warning_keyword_counts,\n            'critical_matches': critical_matches,\n            'warning_matches': warning_matches,\n        }\n        thresholds = {\n            'critical_log_keywords': '|'.join(critical_keywords),\n            'warning_log_keywords': '|'.join(warning_keywords),\n        }\n        threshold_summary = (\n            'critical_log_keywords=' + thresholds['critical_log_keywords'] +\n            '; warning_log_keywords=' + thresholds['warning_log_keywords']\n        )\n\n        if critical_matches:\n            return self.fail(\n                '치명적 커널 로그 감지',\n                message=(\n                    '치명적 키워드가 포함된 dmesg 로그가 확인되었습니다. '\n                    '키워드별 검출 건수: ' + self._format_keyword_counts(critical_keyword_counts) +\n                    '. 임계치: ' + threshold_summary\n                ),\n                stdout=(out or '').strip(),\n                stderr=(err or '').strip(),\n            )\n\n        if warning_matches:\n            return self.warn(\n                metrics=metrics,\n                thresholds=thresholds,\n                reasons='경고 키워드가 포함된 dmesg 로그가 확인되어 추가 점검이 필요합니다. 키워드별 검출 건수: ' + self._format_keyword_counts(warning_keyword_counts),\n                message=(\n                    '경고 수준의 dmesg 로그가 확인되었습니다. '\n                    '키워드별 검출 건수: ' + self._format_keyword_counts(warning_keyword_counts) +\n                    '. 임계치: ' + threshold_summary\n                ),\n            )\n\n        return self.ok(\n            metrics=metrics,\n            thresholds=thresholds,\n            reasons=(\n                '치명적 및 경고 키워드가 모두 검출되지 않았습니다. '\n                'critical: ' + self._format_keyword_counts(critical_keyword_counts) +\n                '; warning: ' + self._format_keyword_counts(warning_keyword_counts)\n            ),\n            message=(\n                'dmesg 시스템 로그 점검이 정상 수행되었습니다. '\n                '미검출 키워드 현황 - critical: ' + self._format_keyword_counts(critical_keyword_counts) +\n                '; warning: ' + self._format_keyword_counts(warning_keyword_counts) +\n                '. 임계치: ' + threshold_summary\n            ),\n        )\n\n\nCHECK_CLASS = Check\n",
      "check_script_lines": [
        "# -*- coding: utf-8 -*-",
        "",
        "from .common._base import BaseCheck",
        "",
        "",
        "DMESG_COMMAND = 'dmesg'",
        "",
        "",
        "class Check(BaseCheck):",
        "    USE_HOST_CONNECTION = True",
        "    CONNECTION_METHOD = 'ssh'",
        "",
        "    def _split_keywords(self, raw_value):",
        "        return [",
        "            token.strip()",
        "            for token in str(raw_value or '').split('|')",
        "            if token.strip()",
        "        ]",
        "",
        "    def _find_matches(self, lines, keywords):",
        "        matches = []",
        "",
        "        for line in lines:",
        "            line_lower = line.lower()",
        "            matched_keywords = [",
        "                keyword",
        "                for keyword in keywords",
        "                if keyword.lower() in line_lower",
        "            ]",
        "            if not matched_keywords:",
        "                continue",
        "            matches.append({",
        "                'line': line,",
        "                'matched_keywords': matched_keywords,",
        "            })",
        "",
        "        return matches",
        "",
        "    def _count_keywords(self, matches, keywords):",
        "        counts = {keyword: 0 for keyword in keywords}",
        "",
        "        for match in matches:",
        "            for keyword in match.get('matched_keywords', []):",
        "                if keyword in counts:",
        "                    counts[keyword] += 1",
        "",
        "        return counts",
        "",
        "    def _format_keyword_counts(self, counts):",
        "        return ', '.join(",
        "            f'{keyword}={count}건'",
        "            for keyword, count in counts.items()",
        "        )",
        "",
        "    def run(self):",
        "        critical_keywords = self._split_keywords(",
        "            self.get_threshold_var('critical_log_keywords', default='', value_type='str')",
        "        )",
        "        warning_keywords = self._split_keywords(",
        "            self.get_threshold_var('warning_log_keywords', default='', value_type='str')",
        "        )",
        "",
        "        if not critical_keywords and not warning_keywords:",
        "            return self.fail(",
        "                '임계치 미정의',",
        "                message='critical_log_keywords 또는 warning_log_keywords 가 정의되어 있지 않습니다.',",
        "            )",
        "",
        "        rc, out, err = self._ssh(DMESG_COMMAND)",
        "",
        "        if self._is_connection_error(rc, err):",
        "            return self.fail(",
        "                '호스트 연결 실패',",
        "                message=(err or 'SSH 연결 확인에 실패했습니다.').strip(),",
        "                stderr=(err or '').strip(),",
        "            )",
        "",
        "        if rc != 0:",
        "            return self.fail(",
        "                '점검 명령 실행 실패',",
        "                message='dmesg 명령 실행에 실패했습니다.',",
        "                stdout=(out or '').strip(),",
        "                stderr=(err or '').strip(),",
        "            )",
        "",
        "        lines = [line.strip() for line in (out or '').splitlines() if line.strip()]",
        "        if not lines:",
        "            return self.fail(",
        "                '시스템 로그 정보 없음',",
        "                message='dmesg 결과가 비어 있습니다.',",
        "                stdout=(out or '').strip(),",
        "                stderr=(err or '').strip(),",
        "            )",
        "",
        "        critical_matches = self._find_matches(lines, critical_keywords)",
        "        warning_matches = self._find_matches(lines, warning_keywords)",
        "        critical_keyword_counts = self._count_keywords(critical_matches, critical_keywords)",
        "        warning_keyword_counts = self._count_keywords(warning_matches, warning_keywords)",
        "",
        "        metrics = {",
        "            'log_line_count': len(lines),",
        "            'critical_match_count': len(critical_matches),",
        "            'warning_match_count': len(warning_matches),",
        "            'critical_keyword_counts': critical_keyword_counts,",
        "            'warning_keyword_counts': warning_keyword_counts,",
        "            'critical_matches': critical_matches,",
        "            'warning_matches': warning_matches,",
        "        }",
        "        thresholds = {",
        "            'critical_log_keywords': '|'.join(critical_keywords),",
        "            'warning_log_keywords': '|'.join(warning_keywords),",
        "        }",
        "        threshold_summary = (",
        "            'critical_log_keywords=' + thresholds['critical_log_keywords'] +",
        "            '; warning_log_keywords=' + thresholds['warning_log_keywords']",
        "        )",
        "",
        "        if critical_matches:",
        "            return self.fail(",
        "                '치명적 커널 로그 감지',",
        "                message=(",
        "                    '치명적 키워드가 포함된 dmesg 로그가 확인되었습니다. '",
        "                    '키워드별 검출 건수: ' + self._format_keyword_counts(critical_keyword_counts) +",
        "                    '. 임계치: ' + threshold_summary",
        "                ),",
        "                stdout=(out or '').strip(),",
        "                stderr=(err or '').strip(),",
        "            )",
        "",
        "        if warning_matches:",
        "            return self.warn(",
        "                metrics=metrics,",
        "                thresholds=thresholds,",
        "                reasons='경고 키워드가 포함된 dmesg 로그가 확인되어 추가 점검이 필요합니다. 키워드별 검출 건수: ' + self._format_keyword_counts(warning_keyword_counts),",
        "                message=(",
        "                    '경고 수준의 dmesg 로그가 확인되었습니다. '",
        "                    '키워드별 검출 건수: ' + self._format_keyword_counts(warning_keyword_counts) +",
        "                    '. 임계치: ' + threshold_summary",
        "                ),",
        "            )",
        "",
        "        return self.ok(",
        "            metrics=metrics,",
        "            thresholds=thresholds,",
        "            reasons=(",
        "                '치명적 및 경고 키워드가 모두 검출되지 않았습니다. '",
        "                'critical: ' + self._format_keyword_counts(critical_keyword_counts) +",
        "                '; warning: ' + self._format_keyword_counts(warning_keyword_counts)",
        "            ),",
        "            message=(",
        "                'dmesg 시스템 로그 점검이 정상 수행되었습니다. '",
        "                '미검출 키워드 현황 - critical: ' + self._format_keyword_counts(critical_keyword_counts) +",
        "                '; warning: ' + self._format_keyword_counts(warning_keyword_counts) +",
        "                '. 임계치: ' + threshold_summary",
        "            ),",
        "        )",
        "",
        "",
        "CHECK_CLASS = Check"
      ]
    }
  ],
  "results": [
    {
      "inspection_code": "U-REPLAY-DMESG-01",
      "item_id": 90012,
      "application_id": 111,
      "application_type_id": 10,
      "application_type_name": "LINUX",
      "application_name": "A",
      "application_family_name": "A",
      "threshold_list": [
        {
          "name": "critical_log_keywords",
          "value1": "Out of memory|I/O error|Buffer I/O error|Call Trace|segfault|filesystem error|kernel panic"
        },
        {
          "name": "warning_log_keywords",
          "value1": "temperature above threshold|cpu clock throttled|throttled|reset|timeout"
        }
      ],
      "status": "fail",
      "error": "치명적 커널 로그 감지",
      "message": "치명적 키워드가 포함된 dmesg 로그가 확인되었습니다. 키워드별 검출 건수: Out of memory=1건, I/O error=2건, Buffer I/O error=1건, Call Trace=0건, segfault=0건, filesystem error=0건, kernel panic=0건. 임계치: critical_log_keywords=Out of memory|I/O error|Buffer I/O error|Call Trace|segfault|filesystem error|kernel panic; warning_log_keywords=temperature above threshold|cpu clock throttled|throttled|reset|timeout",
      "stdout": "[    0.000000] Linux version 5.14.0-611.13.1.el9_7.x86_64\n[    1.234567] ata1: SATA link up 6.0 Gbps\n[    2.345678] EXT4-fs (sda1): mounted filesystem with ordered data mode\n[   15.456789] device-mapper: multipath: version 1.14.0 loaded\n[  120.567890] Out of memory: Killed process 1234 (java) total-vm:1048576kB\n[  180.678901] blk_update_request: I/O error, dev sda, sector 123456\n[  181.789012] Buffer I/O error on dev sda1, logical block 15432\n[  250.890123] CPU0: Core temperature above threshold, cpu clock throttled",
      "stdout_lines": [
        "[    0.000000] Linux version 5.14.0-611.13.1.el9_7.x86_64",
        "[    1.234567] ata1: SATA link up 6.0 Gbps",
        "[    2.345678] EXT4-fs (sda1): mounted filesystem with ordered data mode",
        "[   15.456789] device-mapper: multipath: version 1.14.0 loaded",
        "[  120.567890] Out of memory: Killed process 1234 (java) total-vm:1048576kB",
        "[  180.678901] blk_update_request: I/O error, dev sda, sector 123456",
        "[  181.789012] Buffer I/O error on dev sda1, logical block 15432",
        "[  250.890123] CPU0: Core temperature above threshold, cpu clock throttled"
      ],
      "stderr": "",
      "raw_output": "[점검 단계 1]\n - 실행 명령어: dmesg\n - 명령 종료코드: rc=0 (정상 종료)\n - 출력 내용: [    0.000000] Linux version 5.14.0-611.13.1.el9_7.x86_64\n[    1.234567] ata1: SATA link up 6.0 Gbps\n[    2.345678] EXT4-fs (sda1): mounted filesystem with ordered data mode\n[   15.456789] device-mapper: multipath: version 1.14.0 loaded\n[  120.567890] Out of memory: Killed process 1234 (java) total-vm:1048576kB\n[  180.678901] blk_update_request: I/O error, dev sda, sector 123456\n[  181.789012] Buffer I/O error on dev sda1, logical block 15432\n[  250.890123] CPU0: Core temperature above threshold, cpu clock throttled",
      "raw_output_lines": [
        "[점검 단계 1]",
        " - 실행 명령어: dmesg",
        " - 명령 종료코드: rc=0 (정상 종료)",
        " - 출력 내용: [    0.000000] Linux version 5.14.0-611.13.1.el9_7.x86_64",
        "[    1.234567] ata1: SATA link up 6.0 Gbps",
        "[    2.345678] EXT4-fs (sda1): mounted filesystem with ordered data mode",
        "[   15.456789] device-mapper: multipath: version 1.14.0 loaded",
        "[  120.567890] Out of memory: Killed process 1234 (java) total-vm:1048576kB",
        "[  180.678901] blk_update_request: I/O error, dev sda, sector 123456",
        "[  181.789012] Buffer I/O error on dev sda1, logical block 15432",
        "[  250.890123] CPU0: Core temperature above threshold, cpu clock throttled"
      ]
    }
  ],
  "failed_items": [
    "U-REPLAY-DMESG-01"
  ]
}
